{"chunk_definitions":[{"chunk_id":"cw32hq3kgx02v","chunk_label":"unnamed-chunk-1","document_id":"4A66670A","expansion_state":0,"options":{"engine":"r","label":"unnamed-chunk-1"},"row":14,"row_count":1,"visible":true},{"chunk_id":"c9dvqgoqeovt3","chunk_label":"unnamed-chunk-2","document_id":"4A66670A","expansion_state":0,"options":{"engine":"r","label":"unnamed-chunk-2"},"row":18,"row_count":1,"visible":true},{"chunk_id":"cgeov1b8tn6mq","chunk_label":"unnamed-chunk-3","document_id":"4A66670A","expansion_state":0,"options":{"engine":"r","label":"unnamed-chunk-3"},"row":29,"row_count":1,"visible":true},{"chunk_id":"cr9ebg8u90381","chunk_label":"unnamed-chunk-4","document_id":"4A66670A","expansion_state":0,"options":{"engine":"r","label":"unnamed-chunk-4"},"row":36,"row_count":1,"visible":true},{"chunk_id":"cagisnyj7wlim","chunk_label":"unnamed-chunk-5","document_id":"4A66670A","expansion_state":0,"options":{"engine":"r","label":"unnamed-chunk-5"},"row":46,"row_count":1,"visible":true},{"chunk_id":"c2pp1bhvdfg78","chunk_label":"unnamed-chunk-6","document_id":"4A66670A","expansion_state":0,"options":{"engine":"r","label":"unnamed-chunk-6"},"row":51,"row_count":1,"visible":true},{"chunk_id":"cudf5rryx7ck8","chunk_label":"unnamed-chunk-7","document_id":"4A66670A","expansion_state":0,"options":{"engine":"r","label":"unnamed-chunk-7"},"row":56,"row_count":1,"visible":true},{"chunk_id":"c2wdcwlaboaic","chunk_label":"unnamed-chunk-8","document_id":"4A66670A","expansion_state":0,"options":{"engine":"r","label":"unnamed-chunk-8"},"row":61,"row_count":1,"visible":true},{"chunk_id":"cvd9nwkioilkw","chunk_label":"unnamed-chunk-9","document_id":"4A66670A","expansion_state":0,"options":{"engine":"r","label":"unnamed-chunk-9"},"row":67,"row_count":1,"visible":true}],"doc_write_time":1558431768}